openbb_orats/__init__.py
openbb_orats/models/__init__.py
openbb_orats/models/tickers.py
openbb_orats/provider.py
openbb_orats/router.py
openbb_orats/utils/__init__.py
openbb_orats/utils/helpers.py
openbb_orats-1.0.1.dist-info/entry_points.txt
openbb_orats-1.0.1.dist-info/METADATA
openbb_orats-1.0.1.dist-info/WHEEL
openbb_orats-1.0.1.dist-info/RECORD
