Metadata-Version: 2.1
Name: openbb-orats
Version: 1.0.1
Summary: Connecting OpenBB to ORATS Option Data Source
Author: Jennings Fantini
Author-email: jennings@humblfinance.io
Requires-Python: >=3.8.1,<3.12
Classifier: Programming Language :: Python :: 3
Classifier: Programming Language :: Python :: 3.9
Classifier: Programming Language :: Python :: 3.10
Classifier: Programming Language :: Python :: 3.11
Requires-Dist: build (>=1.0.3,<2.0.0)
Requires-Dist: openbb-core (>=1.1.0,<2.0.0)
Requires-Dist: openbb-devtools (>=1.0.0b1,<2.0.0)
